MANIFEST.in
README.md
setup.py
nfe/__init__.py
nfe/gateways/__init__.py
nfe/gateways/saopaulo.py
nfe/samples/__init__.py
nfe/samples/bla.py
nfe/samples/cancelNfe.py
nfe/samples/consultNfes.py
nfe/samples/formatter.py
nfe/samples/regexParser.py
nfe/samples/requester.py
nfe/samples/sendRps.py
nfe/samples/testsDigest.py
nfe/utils/__init__.py
nfe/utils/certificate.py
nfe/utils/compatibility.py
nfe/utils/currency.py
nfe/utils/response.py
nfe/utils/rps.py
nfe/utils/rsa.py
nfe/utils/schemas.py
starkbank_nfe.egg-info/PKG-INFO
starkbank_nfe.egg-info/SOURCES.txt
starkbank_nfe.egg-info/dependency_links.txt
starkbank_nfe.egg-info/requires.txt
starkbank_nfe.egg-info/top_level.txt