Metadata-Version: 2.1
Name: starkbank-nfe
Version: 0.1.5
Summary: Python xml signer and webservice requester
Home-page: https://github.com/starkbank/nfe
Author: Stark Bank
Author-email: developers@starkbank.com
License: MIT License
Keywords: nfe,nfse,xml,xml signer,stark bank,starkbank
Platform: UNKNOWN
